setup.py
ImportStackmobData/__init__.py
ImportStackmobData/import-stackmob-to-apiOmat
import_stackmob_to_apiOmat.egg-info/PKG-INFO
import_stackmob_to_apiOmat.egg-info/SOURCES.txt
import_stackmob_to_apiOmat.egg-info/dependency_links.txt
import_stackmob_to_apiOmat.egg-info/top_level.txt