Metadata-Version: 1.0
Name: import-stackmob-to-apiOmat
Version: 1.0
Summary: Import your data from Stackmob to apiOmat
Home-page: https://github.com/apinaut/apiOmat-import-stackmob
Author: UNKNOWN
Author-email: UNKNOWN
License: UNKNOWN
Platform: UNKNOWN
